bijux_rar/__init__.py
bijux_rar/__main__.py
bijux_rar/_version.py
bijux_rar/httpapi.py
bijux_rar/security.py
bijux_rar/system_contract.py
bijux_rar/boundaries/__init__.py
bijux_rar/boundaries/cli/__init__.py
bijux_rar/boundaries/cli/init.py
bijux_rar/boundaries/cli/main.py
bijux_rar/boundaries/serde/__init__.py
bijux_rar/boundaries/serde/json_canonical.py
bijux_rar/boundaries/serde/json_file.py
bijux_rar/boundaries/serde/trace_jsonl.py
bijux_rar/core/__init__.py
bijux_rar/core/fingerprints.py
bijux_rar/core/invariants.py
bijux_rar/core/rar_types.py
bijux_rar/rar/__init__.py
bijux_rar/rar/app.py
bijux_rar/rar/eval/__init__.py
bijux_rar/rar/eval/suite.py
bijux_rar/rar/execution/__init__.py
bijux_rar/rar/execution/executor.py
bijux_rar/rar/execution/frozen_runtime.py
bijux_rar/rar/execution/runtime.py
bijux_rar/rar/execution/tools.py
bijux_rar/rar/planning/__init__.py
bijux_rar/rar/planning/ir.py
bijux_rar/rar/planning/planner.py
bijux_rar/rar/reasoning/__init__.py
bijux_rar/rar/reasoning/backend.py
bijux_rar/rar/reasoning/extractive.py
bijux_rar/rar/retrieval/__init__.py
bijux_rar/rar/retrieval/bm25.py
bijux_rar/rar/retrieval/chunked_bm25.py
bijux_rar/rar/retrieval/chunking.py
bijux_rar/rar/retrieval/corpus.py
bijux_rar/rar/skeleton/__init__.py
bijux_rar/rar/skeleton/fake_runtime.py
bijux_rar/rar/skeleton/run_builder.py
bijux_rar/rar/traces/__init__.py
bijux_rar/rar/traces/checksum.py
bijux_rar/rar/traces/diff.py
bijux_rar/rar/traces/replay.py
bijux_rar/rar/verification/__init__.py
bijux_rar/rar/verification/checks.py
bijux_rar/rar/verification/types.py
bijux_rar/rar/verification/verifier.py
bijux_rar-0.1.0.dist-info/METADATA
bijux_rar-0.1.0.dist-info/WHEEL
bijux_rar-0.1.0.dist-info/entry_points.txt
bijux_rar-0.1.0.dist-info/licenses/LICENSE
bijux_rar-0.1.0.dist-info/RECORD
